ruamel.showoutput-0.1.7-py2.7-nspkg.pth
ruamel/showoutput/__init__.py
ruamel.showoutput-0.1.7.dist-info/DESCRIPTION.rst
ruamel.showoutput-0.1.7.dist-info/LICENSE.txt
ruamel.showoutput-0.1.7.dist-info/METADATA
ruamel.showoutput-0.1.7.dist-info/RECORD
ruamel.showoutput-0.1.7.dist-info/WHEEL
ruamel.showoutput-0.1.7.dist-info/metadata.json
ruamel.showoutput-0.1.7.dist-info/namespace_packages.txt
ruamel.showoutput-0.1.7.dist-info/top_level.txt
