Metadata-Version: 2.0
Name: ruamel.showoutput
Version: 0.1.7
Summary: like subprocess.check_output(), but showing progress
Home-page: https://bitbucket.org/ruamel/showoutput
Author: Anthon van der Neut
Author-email: a.van.der.neut@ruamel.eu
License: MIT
Platform: UNKNOWN
Classifier: Development Status :: 4 - Beta
Classifier: Intended Audience :: Developers
Classifier: License :: OSI Approved :: MIT License
Classifier: Operating System :: OS Independent
Classifier: Programming Language :: Python
